mtscomp.py
mtscomp-1.0.2.dist-info/LICENSE.md
mtscomp-1.0.2.dist-info/METADATA
mtscomp-1.0.2.dist-info/WHEEL
mtscomp-1.0.2.dist-info/entry_points.txt
mtscomp-1.0.2.dist-info/top_level.txt
mtscomp-1.0.2.dist-info/RECORD
