Metadata-Version: 2.1
Name: mtscomp
Version: 1.0.2
Summary: Lossless compression for electrophysiology time-series
Home-page: https://github.com/int-brain-lab/mtscomp
Author: Cyrille Rossant (International Brain Laboratory)
Author-email: cyrille.rossant@gmail.com
License: BSD
Keywords: lossless,compresssion,electrophysiology,neuroscience
Platform: UNKNOWN
Classifier: Development Status :: 4 - Beta
Classifier: Intended Audience :: Developers
Classifier: License :: OSI Approved :: BSD License
Classifier: Natural Language :: English
Classifier: Programming Language :: Python :: 3
Classifier: Programming Language :: Python :: 3.7
